sockpuppet/__init__.py
sockpuppet/apps.py
sockpuppet/channel.py
sockpuppet/consumer.py
sockpuppet/element.py
sockpuppet/reflex.py
sockpuppet/routing.py
sockpuppet/utils.py
sockpuppet/js/sockpuppet.js
sockpuppet/management/commands/__init__.py
sockpuppet/management/commands/_base.py
sockpuppet/management/commands/generate_reflex.py
sockpuppet/management/commands/initial_sockpuppet.py
sockpuppet/static/sockpuppet/sockpuppet.js
sockpuppet/templates/sockpuppet/scaffolds/application.js
sockpuppet/templates/sockpuppet/scaffolds/controller.js
sockpuppet/templates/sockpuppet/scaffolds/reflex.py
sockpuppet/templates/sockpuppet/scaffolds/template.html
sockpuppet/templates/sockpuppet/scaffolds/view.py
sockpuppet/templates/sockpuppet/scaffolds/webpack.html
sockpuppet/templatetags/__init__.py
sockpuppet/templatetags/sockpuppet.py
sockpuppet/test_utils/__init__.py
sockpuppet/test_utils/factory.py
django_sockpuppet-0.6.0.dist-info/LICENSE
django_sockpuppet-0.6.0.dist-info/METADATA
django_sockpuppet-0.6.0.dist-info/WHEEL
django_sockpuppet-0.6.0.dist-info/top_level.txt
django_sockpuppet-0.6.0.dist-info/RECORD
