Metadata-Version: 2.1
Name: django-sockpuppet
Version: 0.6.0
Summary: Helping you use websockets in an effective way in views
Home-page: https://github.com/jonathan-s/django-sockpuppet
Author: Jonathan Sundqvist
Author-email: jonathan@argpar.se
License: MIT
Keywords: django-sockpuppet
Platform: UNKNOWN
Classifier: Development Status :: 4 - Beta
Classifier: Framework :: Django :: 2.2
Classifier: Framework :: Django :: 3.0
Classifier: Intended Audience :: Developers
Classifier: Environment :: Web Environment
Classifier: License :: OSI Approved :: BSD License
Classifier: Natural Language :: English
Classifier: Programming Language :: Python :: 3
Classifier: Programming Language :: Python :: 3.5
Classifier: Programming Language :: Python :: 3.6
Classifier: Programming Language :: Python :: 3.7
Requires-Dist: channels
Requires-Dist: channels-redis
Requires-Dist: bs4
Provides-Extra: lxml
Requires-Dist: lxml ; extra == 'lxml'
Requires-Dist: cssselect ; extra == 'lxml'
